{
  "project_info": {
    "project_number": "394657733193",
    "project_id": "instagram-clone-28888",
    "storage_bucket": "instagram-clone-28888.appspot.com"
  },
  "client": [
    {
      "client_info": {
        "mobilesdk_app_id": "1:394657733193:android:a59f3f0fe7a976a1bcbd98",
        "android_client_info": {
          "package_name": "com.example.instagram_clone_flutter"
        }
      },
      "oauth_client": [],
      "api_key": [
        {
          "current_key": "AIzaSyBgPrSJSVQsYEh4t2pYdtfDqoUEXZNHN6I"
        }
      ],
      "services": {
        "appinvite_service": {
          "other_platform_oauth_client": []
        }
      }
    }
  ],
  "configuration_version": "1"
}